pyjpgclipboard/__init__.py
pyjpgclipboard/clipboard_darwin.py
pyjpgclipboard/clipboard_linux.py
pyjpgclipboard/clipboard_win32.py
pyjpgclipboard/version.py
pyjpgclipboard-1.0.3.dist-info/LICENSE
pyjpgclipboard-1.0.3.dist-info/METADATA
pyjpgclipboard-1.0.3.dist-info/WHEEL
pyjpgclipboard-1.0.3.dist-info/top_level.txt
pyjpgclipboard-1.0.3.dist-info/RECORD
