Metadata-Version: 2.1
Name: pyjpgclipboard
Version: 1.0.3
Summary: Server to run ytclip.
Home-page: https://github.com/zackees/pyjpgclipboard
Author: Zach Vorhies
Author-email: dont@email.me
License: MIT
Platform: UNKNOWN
Classifier: License :: OSI Approved :: MIT License
Classifier: Programming Language :: Python :: 3.6
Classifier: Programming Language :: Python :: 3.9
Classifier: Operating System :: Microsoft :: Windows
Classifier: Operating System :: POSIX
Classifier: Operating System :: MacOS :: MacOS X
Classifier: Environment :: Console
Requires-Python: >=3.6.0
Requires-Dist: pywin32 ; sys_platform == "win32"
Provides-Extra: test
Requires-Dist: pytest ; extra == 'test'
